itk/Configuration/RingArtifactConfig.py
itk/Configuration/RingArtifact_snake_case.py
itk/RingArtifactPython.py
itk/_RingArtifactPython.so
itk/itkFourierStripeArtifactImageFilterPython.py
itk_ringartifact-2.0.1.dist-info/METADATA
itk_ringartifact-2.0.1.dist-info/WHEEL
itk_ringartifact-2.0.1.dist-info/entry_points.txt
itk_ringartifact-2.0.1.dist-info/licenses/LICENSE
itk_ringartifact-2.0.1.dist-info/RECORD
