Metadata-Version: 2.1
Name: itk-ringartifact
Version: 2.0.1
Summary: ITK filters to reduce stripe artifacts or ring artifacts common in X-ray computed tomography, focused ion beam images, etc.
Keywords: itk,InsightToolkit
Author-Email: Insight Software Consortium <itk+community@discourse.itk.org>
License:                                  Apache License
Classifier: Development Status :: 4 - Beta
Classifier: Intended Audience :: Developers
Classifier: Intended Audience :: Education
Classifier: Intended Audience :: Healthcare Industry
Classifier: Intended Audience :: Science/Research
Classifier: License :: OSI Approved :: Apache Software License
Classifier: Operating System :: Android
Classifier: Operating System :: MacOS
Classifier: Operating System :: Microsoft :: Windows
Classifier: Operating System :: POSIX
Classifier: Operating System :: Unix
Classifier: Programming Language :: C++
Classifier: Programming Language :: Python
Classifier: Topic :: Scientific/Engineering
Classifier: Topic :: Scientific/Engineering :: Information Analysis
Classifier: Topic :: Scientific/Engineering :: Medical Science Apps.
Classifier: Topic :: Software Development :: Libraries
Project-URL: Download, https://github.com/InsightSoftwareConsortium/ITKRingArtifact
Project-URL: Homepage, https://github.com/InsightSoftwareConsortium/ITKRingArtifact
Requires-Python: >=3.8
Requires-Dist: itk==5.4.*
